README.md
setup.py
grpc_django/__init__.py
grpc_django/apps.py
grpc_django/exceptions.py
grpc_django/interfaces.py
grpc_django/models.py
grpc_django/protobuf_to_dict.py
grpc_django/rpcs.py
grpc_django/server.py
grpc_django/service.py
grpc_django/settings.py
grpc_django/views.py
grpc_django.egg-info/PKG-INFO
grpc_django.egg-info/SOURCES.txt
grpc_django.egg-info/dependency_links.txt
grpc_django.egg-info/requires.txt
grpc_django.egg-info/top_level.txt
grpc_django/management/__init__.py
grpc_django/management/commands/__init__.py
grpc_django/management/commands/generate_grpc_stubs.py
grpc_django/management/commands/run_grpc_server.py
grpc_django/migrations/__init__.py
grpc_django/utils/__init__.py
grpc_django/utils/interceptors/__init__.py
grpc_django/utils/interceptors/_interceptor.py
grpc_django/utils/interceptors/bases.py