Metadata-Version: 2.1
Name: grpc-django
Version: 1.0.0
Summary: gRPC Integration with Django Framework
Home-page: https://github.com/soheltarir/grpc-django
Author: Sohel Tarir
Author-email: sohel.tarir@gmail.com
License: MIT
Platform: UNKNOWN
Classifier: License :: OSI Approved :: MIT License
Classifier: Programming Language :: Python :: 3
Classifier: Programming Language :: Python :: 3.5
Classifier: Programming Language :: Python :: 3.6
Classifier: Programming Language :: Python :: 3.7
Requires-Python: >3.5.0
